{
  "parent": "minecraft:recipes/root",
  "rewards": {
    "recipes": [
      "allthemodium:demonic_wooden_slabs"
    ]
  },
  "criteria": {
    "has_OptionalNamedTag[allthemodium:ancient_stone]_block": {
      "trigger": "minecraft:inventory_changed",
      "conditions": {
        "items": [
          {
            "tag": "allthemodium:demonic_planks"
          }
        ]
      }
    },
    "has_the_recipe": {
      "trigger": "minecraft:recipe_unlocked",
      "conditions": {
        "recipe": "allthemodium:demonic_wooden_slabs"
      }
    }
  },
  "requirements": [
    [
      "has_OptionalNamedTag[allthemodium:ancient_stone]_block",
      "has_the_recipe"
    ]
  ]
}